project_press/__init__.py
project_press/__main__.py
project_press/cli.py
project_press/clone.py
project_press/questions.py
project_press/template.py
project_press/utils.py
project_press/validate.py
project_press-0.9.0.dist-info/LICENSE
project_press-0.9.0.dist-info/METADATA
project_press-0.9.0.dist-info/WHEEL
project_press-0.9.0.dist-info/entry_points.txt
project_press-0.9.0.dist-info/top_level.txt
project_press-0.9.0.dist-info/zip-safe
project_press-0.9.0.dist-info/RECORD
