Metadata-Version: 2.1
Name: project-press
Version: 0.9.0
Summary: A cookiecutter clone
Author-email: Julien Lecomte <julien@lecomte.at>
License: MIT
Project-URL: Homepage, https://gitlab.com/jlecomte/python/project-press
Classifier: License :: OSI Approved :: MIT License
Classifier: Intended Audience :: Developers
Classifier: Development Status :: 4 - Beta
Classifier: Programming Language :: Python :: 3 :: Only
Classifier: Programming Language :: Python :: 3.7
Classifier: Programming Language :: Python :: 3.8
Classifier: Programming Language :: Python :: 3.9
Requires-Python: >=3.7
License-File: LICENSE
Requires-Dist: cerberus
Requires-Dist: imxdparser
Requires-Dist: jinja2
Requires-Dist: prompt-toolkit
Requires-Dist: pyyaml
Requires-Dist: torxtools
